makelive/__init__.py
makelive/__main__.py
makelive/makelive.py
makelive/version.py
makelive-0.6.1.dist-info/entry_points.txt
makelive-0.6.1.dist-info/LICENSE
makelive-0.6.1.dist-info/WHEEL
makelive-0.6.1.dist-info/METADATA
makelive-0.6.1.dist-info/RECORD
