Metadata-Version: 2.1
Name: makelive
Version: 0.6.1
Summary: Add the necessary metadata to photo + video pair so Photos recognizes them as Live Photos when imported
Author-email: Rhet Turnbull <rturnbull+git@gmail.com>
Requires-Python: >3.9
Classifier: License :: OSI Approved :: MIT License
Requires-Dist: cgmetadata>=0.1.6
Requires-Dist: click>=8.0.0
Requires-Dist: pyobjc-core>=9.2
Requires-Dist: pyobjc-framework-AVFoundation>=9.2
Requires-Dist: pyobjc-framework-Contacts>=9.2
Requires-Dist: pyobjc-framework-CoreLocation>=9.2
Requires-Dist: pyobjc-framework-Quartz>=9.2
Requires-Dist: pyobjc-framework-UniformTypeIdentifiers>=9.2
Requires-Dist: wheel>=0.41.2
Requires-Dist: wurlitzer>=3.0.3
Requires-Dist: applecrate>=0.2.0 ; extra == "dev"
Requires-Dist: bump2version==1.0.1 ; extra == "dev"
Requires-Dist: ruff>=0.1.14 ; extra == "lint"
Requires-Dist: pytest>=7.4.2 ; extra == "test"
Requires-Dist: pytest-cov ; extra == "test"
Requires-Dist: mypy>=1.6.1 ; extra == "test"
Project-URL: Home, https://github.com/RhetTbull/makelive
Project-URL: Issues, https://github.com/RhetTbull/makelive/issues
Project-URL: Source, https://github.com/RhetTbull/makelive
Provides-Extra: dev
Provides-Extra: lint
Provides-Extra: test
